whylogs_datasketches.cp38-win_amd64.pyd
whylogs_datasketches-3.4.0.dev6.dist-info/LICENSE
whylogs_datasketches-3.4.0.dev6.dist-info/METADATA
whylogs_datasketches-3.4.0.dev6.dist-info/NOTICE
whylogs_datasketches-3.4.0.dev6.dist-info/WHEEL
whylogs_datasketches-3.4.0.dev6.dist-info/top_level.txt
whylogs_datasketches-3.4.0.dev6.dist-info/RECORD
