Metadata-Version: 2.1
Name: whylogs-datasketches
Version: 3.4.0.dev6
Summary: The fork for whylogs for Apache DataSketches Library for Python
Home-page: https://github.com/whylabs/whylogs-datasketches
Author: Apache Software Foundation
Author-email: support@whylabs.ai
License: Apache License 2.0
Platform: UNKNOWN
License-File: LICENSE
License-File: NOTICE
